package_name_Alisson/__init__.py
package_name_Alisson/file1_name.py
package_name_Alisson/file2_name.py
package_name_Alisson-0.0.1.dist-info/METADATA
package_name_Alisson-0.0.1.dist-info/WHEEL
package_name_Alisson-0.0.1.dist-info/top_level.txt
package_name_Alisson-0.0.1.dist-info/RECORD
